aiforge_manager-1.0.2.dist-info/licenses/LICENSE
core/__init__.py
core/builder.py
core/cli.py
core/exporter.py
core/git_integration.py
core/gui.py
core/local_ai.py
core/parser.py
core/synchronizer.py
core/validator.py
tests/__init__.py
tests/test_builder.py
tests/test_integration.py
tests/test_parser.py
tests/test_synchronizer.py
aiforge_manager-1.0.2.dist-info/METADATA
aiforge_manager-1.0.2.dist-info/WHEEL
aiforge_manager-1.0.2.dist-info/entry_points.txt
aiforge_manager-1.0.2.dist-info/top_level.txt
aiforge_manager-1.0.2.dist-info/RECORD
