Metadata-Version: 2.4
Name: aiforge-manager
Version: 1.0.2
Summary: Bidirectional AI-Project Manager: Transform AI outputs into structured projects and vice versa
Author-email: Giuseppe <giuseppe@users.noreply.github.com>
License: MIT
Project-URL: Homepage, https://github.com/tuo-username/AIForge
Project-URL: Documentation, https://github.com/tuo-username/AIForge/wiki
Project-URL: Issues, https://github.com/tuo-username/AIForge/issues
Project-URL: Source, https://github.com/tuo-username/AIForge
Keywords: ai,code,flutter,python,project,sync,git,llm,developer-tools
Classifier: License :: OSI Approved :: MIT License
Classifier: Programming Language :: Python :: 3
Classifier: Programming Language :: Python :: 3.8
Classifier: Programming Language :: Python :: 3.9
Classifier: Programming Language :: Python :: 3.10
Classifier: Intended Audience :: Developers
Classifier: Operating System :: OS Independent
Classifier: Topic :: Software Development :: Build Tools
Classifier: Topic :: Software Development :: Version Control :: Git
Classifier: Topic :: Utilities
Requires-Python: >=3.8
License-File: LICENSE
Requires-Dist: PyYAML>=6.0
Provides-Extra: local-ai
Requires-Dist: torch>=2.0.0; extra == "local-ai"
Requires-Dist: transformers>=4.30.0; extra == "local-ai"
Requires-Dist: accelerate>=0.20.0; extra == "local-ai"
Provides-Extra: dev
Requires-Dist: pytest>=7.0; extra == "dev"
Requires-Dist: black>=23.0; extra == "dev"
Requires-Dist: mypy>=1.0; extra == "dev"
Dynamic: license-file
